votelib/__init__.py
votelib/candidate.py
votelib/convert.py
votelib/generate.py
votelib/persist.py
votelib/util.py
votelib/vote.py
votelib/component/__init__.py
votelib/component/core.py
votelib/component/divisor.py
votelib/component/pairwin_scorer.py
votelib/component/quota.py
votelib/component/rankscore.py
votelib/component/transfer.py
votelib/crit/__init__.py
votelib/crit/proportionality.py
votelib/crit/yee.py
votelib/evaluate/__init__.py
votelib/evaluate/approval.py
votelib/evaluate/auxiliary.py
votelib/evaluate/cardinal.py
votelib/evaluate/condorcet.py
votelib/evaluate/core.py
votelib/evaluate/openlist.py
votelib/evaluate/proportional.py
votelib/evaluate/sequential.py
votelib/evaluate/threshold.py
votelib/io/__init__.py
votelib/io/blt.py
votelib/io/core.py
votelib/io/stv.py
votelib-0.4.0.dist-info/LICENSE.txt
votelib-0.4.0.dist-info/METADATA
votelib-0.4.0.dist-info/WHEEL
votelib-0.4.0.dist-info/top_level.txt
votelib-0.4.0.dist-info/zip-safe
votelib-0.4.0.dist-info/RECORD
