Metadata-Version: 2.1
Name: votelib
Version: 0.4.0
Summary: Voting evaluation library for Python
Home-page: https://github.com/simberaj/votelib
Author: Jan Šimbera
Author-email: simbera.jan@gmail.com
License: MIT
Keywords: voting election vote electoral apportionment condorcet python
Platform: UNKNOWN
Classifier: Development Status :: 2 - Pre-Alpha
Classifier: Environment :: Console
Classifier: Intended Audience :: Developers
Classifier: License :: OSI Approved :: MIT License
Classifier: Natural Language :: English
Classifier: Programming Language :: Python
Classifier: Programming Language :: Python :: 3
Requires-Python: >=3.7.0
